PyOMA/PyOMA.py
PyOMA/__init__.py
Py_OMA-1.5.dist-info/LICENSE
Py_OMA-1.5.dist-info/METADATA
Py_OMA-1.5.dist-info/WHEEL
Py_OMA-1.5.dist-info/top_level.txt
Py_OMA-1.5.dist-info/RECORD
