Metadata-Version: 2.1
Name: Py-OMA
Version: 1.5
Summary: PyOMA allows the experimental estimation of the modal parameters (natural frequencies, mode shapes, damping ratios) of a structure from measurements of the vibration response in operational condition.
Home-page: https://github.com/dagghe/PyOMA
Author: Dag Pasquale Pasca, Angelo Aloisio, Marco Martino Rosso, Stefanos Sotiropoulos
Author-email: <supportPyOMA@polito.it>
License: GNU General Public License v3 (GPLv3)
Keywords: operational modal analysis,ambient vibration modal test,structural dynamics,frequency domain decomposition,stochastic subspace identification,structural health monitoring
Classifier: Programming Language :: Python :: 3
License-File: LICENSE
Requires-Dist: numpy (==1.23.4)
Requires-Dist: scipy (==1.9.3)
Requires-Dist: pandas (==1.5.1)
Requires-Dist: matplotlib (==3.6.2)
Requires-Dist: seaborn (==0.12.1)
Requires-Dist: mplcursors (==0.5.2)
